LICENSE.txt
MANIFEST.in
README.rst
setup.py
cash/__init__.py
cash/accessory.py
cash/cash.py
cash/converter.py
cash/graph.py
cash.egg-info/PKG-INFO
cash.egg-info/SOURCES.txt
cash.egg-info/dependency_links.txt
cash.egg-info/entry_points.txt
cash.egg-info/requires.txt
cash.egg-info/top_level.txt
cash.egg-info/zip-safe
cash/config/argparse.txt
cash/config/cash.ini
cash/config/messages.txt