Metadata-Version: 1.1
Name: cash
Version: 0.1a1
Summary: The personal finance utility
Home-page: https://github.com/korniichuk/cash/
Author: Ruslan Korniichuk
Author-email: ruslan.korniichuk@gmail.com
License: Public Domain
Download-URL: https://github.com/korniichuk/cash/archive/0.1.zip
Keywords: finance,python3,cash
Platform: Linux
Classifier: Development Status :: 2 - Pre-Alpha
Classifier: Environment :: Console
Classifier: Intended Audience :: End Users/Desktop
Classifier: License :: Public Domain
Classifier: Operating System :: POSIX :: Linux
Classifier: Programming Language :: Python
Classifier: Programming Language :: Python :: 3
Classifier: Programming Language :: Python :: 3.4
Classifier: Programming Language :: Python :: 3 :: Only
Classifier: Topic :: Office/Business
Classifier: Topic :: Office/Business :: Financial
Classifier: Topic :: Utilities
